dep_sync/__init__.py
dep_sync/_dependency.py
dep_sync/_distributions.py
dep_sync/_utils.py
dep_sync/py.typed
dep_sync/scripts.py
dep_sync-0.1.0.dist-info/METADATA
dep_sync-0.1.0.dist-info/WHEEL
dep_sync-0.1.0.dist-info/licenses/LICENSE.txt
dep_sync-0.1.0.dist-info/RECORD
