Metadata-Version: 2.3
Name: dep-sync
Version: 0.1.0
Summary: Synchronize Python environments with dependencies
Project-URL: Homepage, https://ofek.dev/dep-sync/
Project-URL: Sponsor, https://github.com/sponsors/ofek
Project-URL: Changelog, https://ofek.dev/dep-sync/changelog/
Project-URL: Tracker, https://github.com/ofek/dep-sync/issues
Project-URL: Source, https://github.com/ofek/dep-sync
Author-email: Ofek Lev <oss@ofek.dev>
License-Expression: MIT
License-File: LICENSE.txt
Keywords: dependency,environment,install,sync
Classifier: Development Status :: 4 - Beta
Classifier: Programming Language :: Python
Classifier: Programming Language :: Python :: 3.8
Classifier: Programming Language :: Python :: 3.9
Classifier: Programming Language :: Python :: 3.10
Classifier: Programming Language :: Python :: 3.11
Classifier: Programming Language :: Python :: 3.12
Classifier: Programming Language :: Python :: Implementation :: CPython
Classifier: Programming Language :: Python :: Implementation :: PyPy
Requires-Python: >=3.8
Requires-Dist: packaging
